DeepExpressions/__init__.py
DeepExpressions/face/__init__.py
DeepExpressions/face/download_model.py
DeepExpressions/face/face_detector.py
DeepExpressions/image_utils/__init__.py
DeepExpressions/image_utils/bounding_boxes.py
DeepExpressions/image_utils/roi.py
DeepExpressions/image_utils/utils.py
DeepExpressions/models/__init__.py
DeepExpressions/models/fer_model.py
DeepExpressions/models/model_utils.py
DeepExpressions/models/vggface.py
DeepExpressions/train_utils/__init__.py
DeepExpressions/train_utils/data_augmentation.py
DeepExpressions/train_utils/data_loader.py
deep_expressions-0.0.4.dist-info/LICENSE
deep_expressions-0.0.4.dist-info/METADATA
deep_expressions-0.0.4.dist-info/WHEEL
deep_expressions-0.0.4.dist-info/top_level.txt
deep_expressions-0.0.4.dist-info/RECORD
