Metadata-Version: 2.1
Name: deep-expressions
Version: 0.0.4
Summary: A Deep Learning toolkit for Facial Expressions Recognition (FER)
Home-page: https://github.com/deepexpressions/DeepExpressions
Author: Humberto da Silva Neto
Author-email: humberto.nt4@gmail.com
License: MIT
Platform: UNKNOWN
Classifier: Programming Language :: Python :: 3
Classifier: License :: OSI Approved :: MIT License
Classifier: Operating System :: OS Independent
Requires-Dist: opencv-python (>=3.4.0)
Requires-Dist: Pillow (>=6.0.0)
